{
    "name": "Gatto",
    "category": "patchouli:pets",
    "icon": "minecraft:cod",
    "pages": [
        {
            "type": "patchouli:text",
            "text": "$(l)Possibili regali:$()$(br)Cappello con orecchie di gatto, Scheletro di ocelot$(br2)$(l)Addomesticamento$()$(br)Pesce"
        },
        {
            "type": "patchouli:entity",
            "entity": "minecraft:cat",
            "scale": 0.7,
            "text": "Chiamate il vostro gatto arancione Coquito e quello grigio Basil"
        }
    ]
}