{
    "name": "Tuna",
    "category": "patchouli:fish",
    "icon": "aquaculture:tuna",
    "pages": [
        {
            "type": "patchouli:text",
            "text": "$(l)Stats$()$(li):coin: 192$(li)§0🔥 §6Summer§0$(li)Water: Ocean$(li)Weather: Any$(li)Time: Day"
        },
        {
            "type": "patchouli:entity",
            "entity": "aquaculture:tuna",
            "scale": 0.8,
            "rotate": true,
            "text": "This one also wishes it was a Sneep Snorp for some reason."
        }
    ]
}