{
    "name": "Passionfruit 🌼",
    "category": "patchouli:tree_crops",
    "icon": "atmospheric:passion_fruit",
    "pages": [
        {
            "type": "patchouli:text",
            "text": "$(l)Statistiche$()$(li):moneta: 128$(li)🌼 §2Primavera§r§r$(li)Rendita: 1$(li)Stadi di crescita: 8$(br2)$(l)Note$()$(li)Vedi: $(l:trees\/pams\/passionfruit)Albero di Frutto Passione$(\/l)`"
        },
        {
            "type": "patchouli:multiblock",
            "name ": "Passionfruit Tree",
            "enable_visualize": false,
            "multiblock": {
                "mapping": {
                    "0": "minecraft:jungle_leaves",
                    "F": "pamhc2trees:pampassionfruit[age=7]"
                },
                "pattern": [
                    [
                        "0"
                    ],
                    [
                        "F"
                    ]
                ]
            },
            "text": "Multiblock Structure"
        }
    ]
}