{
    "name": "Albero di acacia 🔥",
    "category": "patchouli:trees",
    "icon": "minecraft:acacia_sapling",
    "pages": [
        {
            "type": "patchouli:text",
            "text": "patchouli:testo\n\n$(l)Statistiche$()$(li)🔥 Estate$(li)Prezzo del seme: :moneta: 8$(li)Dimensione: 1x1"
        },
        {
            "type": "patchouli:multiblock",
            "name ": "Patchouli: Multiblocco\n\nQuercia",
            "enable_visualize": false,
            "multiblock": {
                "pattern": [
                    [
                        "        ",
                        "    L   ",
                        "   LLL  ",
                        "  LLLLL ",
                        "   LLL  ",
                        "    L   ",
                        "        ",
                        "        ",
                        "        "
                    ],
                    [
                        "  LLLLL ",
                        " LLLLLLL",
                        " LLLLLLL",
                        " LLLWLLL",
                        " LLLLLLL",
                        " LLLLLLL",
                        "  LLLLL ",
                        "        ",
                        "        "
                    ],
                    [
                        "        ",
                        "        ",
                        "        ",
                        "    W   ",
                        "        ",
                        " LLL    ",
                        " LLL    ",
                        " LLL    ",
                        "        "
                    ],
                    [
                        "        ",
                        "        ",
                        "        ",
                        "    W   ",
                        " LLL    ",
                        "LLLLL   ",
                        "LLWLL   ",
                        "LLLLL   ",
                        " LLL    "
                    ],
                    [
                        "        ",
                        "        ",
                        "        ",
                        "   W    ",
                        "        ",
                        "  W     ",
                        "        ",
                        "        ",
                        "        "
                    ],
                    [
                        "        ",
                        "        ",
                        "        ",
                        "  W     ",
                        "  W     ",
                        "        ",
                        "        ",
                        "        ",
                        "        "
                    ],
                    [
                        "        ",
                        "        ",
                        "        ",
                        "  W     ",
                        "        ",
                        "        ",
                        "        ",
                        "        ",
                        "        "
                    ],
                    [
                        "        ",
                        "        ",
                        "        ",
                        "  W     ",
                        "    0   ",
                        "        ",
                        "        ",
                        "        ",
                        "        "
                    ]
                ],
                "mapping": {
                    "0": "minecraft:air",
                    "L": "minecraft:acacia_leaves",
                    "W": "minecraft:acacia_log[axis=y]"
                }
            }
        }
    ]
}