{
    "name": "Fantasma",
    "category": "patchouli:slimes",
    "icon": "splendid_slimes:plort{plort:{id:\"splendid_slimes:phantom\"}}",
    "pages": [
        {
            "type": "patchouli:text",
            "text": "$(l)Posizioni:$(li)Bioma: Umbra Barrens (Caverna del Cranio)$(br2)$(l)Rischi:$(br)Può far volare e causare l'effetto Hearthstone (teletrasportandoti al tuo punto di partenza) se è arrabbiato."
        },
        {
            "type": "patchouli:entity",
            "name": "Slime Fantasma",
            "entity": "splendid_slimes:splendid_slime{Breed:\"splendid_slimes:phantom\"}",
            "scale": 0.9
        }
    ]
}