{
    "name": "Sparkpod 🌼",
    "category": "patchouli:crops",
    "icon": "society:sparkpod",
    "pages": [
        {
            "type": "patchouli:text",
            "text": "$(l)Stats$()$(li):moneta: 100$(li)🌼 §2Primavera§r$(li)Prezzo del seme: :moneta: 4.096$(li)Resa: 1$(li)Tempo di crescita: 8 giorni"
        },
        {
            "type": "patchouli:multiblock",
            "name ": "Sparkpod: Coltivazione",
            "enable_visualize": false,
            "multiblock": {
                "pattern": [
                    [
                        "0"
                    ],
                    [
                        "F"
                    ]
                ],
                "mapping": {
                    "0": "society:sparkpod[age=8]",
                    "F": "minecraft:farmland[moisture=7]"
                }
            }
        }
    ]
}