{
    "name": "Tubabacco 🌼❆",
    "category": "patchouli:crops",
    "icon": "society:tubabacco_leaf",
    "pages": [
        {
            "type": "patchouli:text",
            "text": "patchouli:testo\n\n$(l)Statistiche$()$(li): monete: 87$(li) 🌼 Primavera§r ❆ §bInverno$(li) Prezzo del seme: 87 monete$(li) Resa: 1$(li) Tempo di crescita: 9 giorni$(br2)$(l)Note$()$(br)Semi acquistati solo dal coltivatore principale"
        },
        {
            "type": "patchouli:multiblock",
            "name ": "Patchouli: Multiblock\n\nTubabacco Crop",
            "enable_visualize": false,
            "multiblock": {
                "pattern": [
                    [
                        "0"
                    ],
                    [
                        "F"
                    ]
                ],
                "mapping": {
                    "0": "society:tubabacco_leaf[age=9]",
                    "F": "minecraft:farmland[moisture=7]"
                }
            }
        }
    ]
}